parsedmarc/__init__.py
parsedmarc/cli.py
parsedmarc/constants.py
parsedmarc/elastic.py
parsedmarc/gelf.py
parsedmarc/kafkaclient.py
parsedmarc/log.py
parsedmarc/loganalytics.py
parsedmarc/opensearch.py
parsedmarc/s3.py
parsedmarc/splunk.py
parsedmarc/syslog.py
parsedmarc/types.py
parsedmarc/utils.py
parsedmarc/webhook.py
parsedmarc/mail/__init__.py
parsedmarc/mail/gmail.py
parsedmarc/mail/graph.py
parsedmarc/mail/imap.py
parsedmarc/mail/mailbox_connection.py
parsedmarc/mail/maildir.py
parsedmarc/resources/__init__.py
parsedmarc/resources/dbip/__init__.py
parsedmarc/resources/dbip/dbip-country-lite.mmdb
parsedmarc/resources/maps/__init__.py
parsedmarc/resources/maps/base_reverse_dns_map.csv
parsedmarc/resources/maps/base_reverse_dns_types.txt
parsedmarc/resources/maps/known_unknown_base_reverse_dns.txt
parsedmarc/resources/maps/psl_overrides.txt
parsedmarc/resources/maps/sortlists.py
parsedmarc-9.0.11.dist-info/METADATA
parsedmarc-9.0.11.dist-info/WHEEL
parsedmarc-9.0.11.dist-info/entry_points.txt
parsedmarc-9.0.11.dist-info/licenses/LICENSE
parsedmarc-9.0.11.dist-info/RECORD
