Metadata-Version: 2.4
Name: parsedmarc
Version: 9.0.11
Summary: A Python package and CLI for parsing aggregate and forensic DMARC reports
Project-URL: Homepage, https://domainaware.github.io/parsedmarc
Author-email: Sean Whalen <whalenster@gmail.com>
License-Expression: Apache-2.0
License-File: LICENSE
Keywords: DMARC,parser,reporting
Classifier: Development Status :: 5 - Production/Stable
Classifier: Intended Audience :: Developers
Classifier: Intended Audience :: Information Technology
Classifier: License :: OSI Approved :: Apache Software License
Classifier: Operating System :: OS Independent
Classifier: Programming Language :: Python :: 3
Requires-Python: >=3.9
Requires-Dist: azure-identity>=1.8.0
Requires-Dist: azure-monitor-ingestion>=1.0.0
Requires-Dist: boto3>=1.16.63
Requires-Dist: dateparser>=1.1.1
Requires-Dist: dnspython>=2.0.0
Requires-Dist: elasticsearch-dsl==7.4.0
Requires-Dist: elasticsearch<7.14.0
Requires-Dist: expiringdict>=1.1.4
Requires-Dist: geoip2>=3.0.0
Requires-Dist: google-api-core>=2.4.0
Requires-Dist: google-api-python-client>=2.35.0
Requires-Dist: google-auth-httplib2>=0.1.0
Requires-Dist: google-auth-oauthlib>=0.4.6
Requires-Dist: google-auth>=2.3.3
Requires-Dist: imapclient>=2.1.0
Requires-Dist: kafka-python-ng>=2.2.2
Requires-Dist: lxml>=4.4.0
Requires-Dist: mailsuite>=1.11.2
Requires-Dist: msgraph-core==0.2.2
Requires-Dist: opensearch-py<=3.0.0,>=2.4.2
Requires-Dist: publicsuffixlist>=0.10.0
Requires-Dist: pygelf>=0.4.2
Requires-Dist: pyyaml>=6.0.3
Requires-Dist: requests>=2.22.0
Requires-Dist: tqdm>=4.31.1
Requires-Dist: urllib3>=1.25.7
Requires-Dist: xmltodict>=0.12.0
Provides-Extra: build
Requires-Dist: hatch>=1.14.0; extra == 'build'
Requires-Dist: myst-parser[linkify]; extra == 'build'
Requires-Dist: nose; extra == 'build'
Requires-Dist: pytest; extra == 'build'
Requires-Dist: pytest-cov; extra == 'build'
Requires-Dist: ruff; extra == 'build'
Requires-Dist: sphinx; extra == 'build'
Requires-Dist: sphinx-rtd-theme; extra == 'build'
